Polygon_Get/__init__.py
Polygon_Get/getdata.py
Polygon_get-0.1.0.dist-info/METADATA
Polygon_get-0.1.0.dist-info/WHEEL
Polygon_get-0.1.0.dist-info/top_level.txt
Polygon_get-0.1.0.dist-info/RECORD
