Metadata-Version: 2.1
Name: Polygon-get
Version: 0.1.0
Summary: Demo library
Home-page: https://polygonget.readthedocs.io/
Author: ds6809
Author-email: ds6809@nyu.edu.com
License: MIT
Platform: UNKNOWN
Classifier: Intended Audience :: Developers
Classifier: License :: OSI Approved :: MIT License
Classifier: Programming Language :: Python
Classifier: Programming Language :: Python :: 3
Classifier: Programming Language :: Python :: 3.6
Classifier: Programming Language :: Python :: 3.7
Classifier: Programming Language :: Python :: 3.8
Classifier: Programming Language :: Python :: 3.9
Classifier: Operating System :: OS Independent
Requires-Dist: math
